[
  {
    "id": "1",
    "title": "3D 에셋 거래용 이커머스 플랫폼",
    "description": "고급 기능과 원활한 사용자 경험을 갖춘 현대적인 이커머스 플랫폼 입니다.",
    "longDescription": "현대적인 웹 기술로 구축된 3D 에셋 거래용 이커머스 플랫폼입니다. 이 프로젝트는 제품 상세페이지, 장바구니 관리, 결제 프로세스, 관리자 대시보드를 포함한 완전한 e-커머스 쇼핑 경험을 제공합니다.",
    "image": "/e-commerce.jpg",
    "thumbnail": "/e-commerce.jpg",
    "tags": [
      "e-commerce",
      "쇼핑몰",
      "모바일 최적화",
      "SEO 최적화",
      "3D 에셋 거래 솔루션",
      "플랫폼"
    ],
    "category": "웹 개발",
    "liveUrl": "https://www.acon3d.com/ko",
    "technologies": [
      "React",
      "Next.js",
      "TypeScript",
      "MUI(material UI)",
      "Emotion",
      "Styled-components",
      "Context API",
      "Recoil",
      "Zustand",
      "GraphQL",
      "REST API"
    ],
    "features": [
      "Next.js 캐싱 전략에따른 상세페이지 최적화(ISR, SSR, SSG)",
      "SEO 최적화",
      "반응형 디자인",
      "검색 및 필터가 있는 상품 검색",
      "장바구니 및 결제",
      "사용자 인증",
      "관리자 대시보드",
      "판매자 대시보드",
      "결제/주문"
    ]
  },
  {
    "id": "2",
    "title": "디자인 시스템",
    "description": "재사용 가능한 컴포넌트를 갖춘 웹 애플리케이션용 포괄적인 디자인 시스템의 쇼케이스 웹사이트",
    "longDescription": "MUI(material UI)를 기반으로 자사 브랜드룩을 적용시킨 웹 사이트입니다. 컴포넌트 라이브러리, 디자인 토큰, 문서를 포함합니다.",
    "image": "/mui-extend.jpg",
    "thumbnail": "/mui-extend.jpg",
    "tags": ["Design System", "UI/UX", "Figma"],
    "category": "디자인",
    "liveUrl": "https://mui-extend.vercel.app/",
    "technologies": [
      "React",
      "Next.js",
      "MUI(material UI)",
      "Shadcn/ui",
      "Tailwind CSS"
    ],
    "features": [
      "컴포넌트 라이브러리",
      "반응형 디자인",
      "디자인 토큰",
      "접근성 가이드라인",
      "문서화"
    ]
  },
  {
    "id": "8",
    "title": "리그오브레전드 전적검색 웹사이트",
    "description": "라이엇 게임즈의 리그오브레전드 전적검색 웹사이트 입니다.",
    "longDescription": "라이엇 게임즈의 리그오브레전드 전적검색 웹사이트 입니다. 리그오브레전드 전적검색 솔루션을 제공 하기위한 다양한 기능들이 포함되어 있습니다.",
    "image": "/ggr.jpg",
    "thumbnail": "/ggr.jpg",
    "tags": ["사이드 프로젝트", "웹사이트", "모바일", "게임 전적검색"],
    "category": "웹 개발",
    "liveUrl": "https://good-game-record.vercel.app/",
    "technologies": [
      "React",
      "Next.js",
      "Shadcn/ui",
      "Tailwind CSS",
      "Riot Games API"
    ],
    "features": ["반응형 디자인", "게임 전적검색", "데이터 시각화"]
  },
  {
    "id": "7",
    "title": "기업/협회 홍보 웹사이트",
    "description": "반응형 웹사이트를 제공하며, 원활한 사용자 경험을 갖춘 웹사이트 입니다.",
    "longDescription": "기업/협회 홍보 웹사이트 입니다. 기업/협회 홍보 솔루션을 제공 하기위한 다양한 기능들이 포함되어 있습니다.",
    "image": "/kisa.jpg",
    "thumbnail": "/kisa.jpg",
    "tags": ["기업/협회", "웹사이트", "모바일 최적화"],
    "category": "웹 개발",
    "liveUrl": "https://www.acon3d.com/ko",
    "technologies": [
      "React",
      "Next.js",
      "TypeScript",
      "PHP",
      "Javascript",
      "CSS3",
      "Bootstrap"
    ],
    "features": ["반응형 디자인", "조직도", "뉴스", "게시판", "인터렉션"]
  },
  {
    "id": "3",
    "title": "에그다이닝 모바일 앱",
    "description": "Webview로 제작된 모바일 애플리케이션",
    "longDescription": "Webview로 제작된 모바일 애플리케이션입니다. 예약 솔루션을 제공 하기위한 다양한 기능들이 포함되어 있습니다.",
    "image": "/egg.jpg",
    "thumbnail": "/egg.jpg",
    "tags": [
      "Webview",
      "예약 솔루션",
      "애플리케이션",
      "모바일 최적화",
      "SEO 최적화"
    ],
    "category": "모바일",
    "liveUrl": "https://play.google.com/store/apps/details?id=com.eggapp&hl=ko",
    "technologies": [
      "React",
      "Next.js",
      "TypeScript",
      "Emotion",
      "React-hook-form",
      "Zustand",
      "REST API"
    ],
    "features": [
      "예약 기능",
      "매장 탐색 기능",
      "그 외 예약 플로우에 따른 필요한 페이지 제공"
    ]
  },
  {
    "id": "4",
    "title": "KT 통화비서 예약솔루션",
    "description": "KT 통화비서 내부에 자사 예약솔루션을 웹뷰 형태로 제공",
    "longDescription": "KT 통화비서 어플리케이션 내부 자사 예약 솔루션을 웹뷰 형태로 제공하여 예약기능 제공",
    "image": "/kt.jpg",
    "thumbnail": "/kt.jpg",
    "tags": [
      "Webview",
      "예약 솔루션",
      "애플리케이션",
      "모바일 최적화",
      "SEO 최적화"
    ],
    "category": "모바일",
    "liveUrl": "https://play.google.com/store/apps/details?id=com.ktaica&hl=ko",
    "technologies": [
      "React",
      "Next.js",
      "TypeScript",
      "Emotion",
      "React-hook-form",
      "Zustand",
      "REST API"
    ],
    "features": [
      "예약 기능",
      "매장 탐색 기능",
      "그 외 예약 플로우에 따른 필요한 페이지 제공"
    ]
  },
  {
    "id": "6",
    "title": "디자인 시스템",
    "description": "재사용 가능한 컴포넌트를 갖춘 웹 애플리케이션용 포괄적인 디자인 시스템의 쇼케이스 웹사이트",
    "longDescription": "자사 UI를 기반으로 브랜드룩을 적용시킨 웹 사이트입니다. 컴포넌트 라이브러리, 디자인 토큰, 문서를 포함합니다.",
    "image": "/mania-framework.jpg",
    "thumbnail": "/mania-framework.jpg",
    "tags": ["Design System", "UI/UX", "Photoshop", "Javscript"],
    "category": "디자인",
    "liveUrl": "https://imisolver.github.io/maniaframe/#/",
    "technologies": ["React(CRA)", "SCSS", "Javascript"],
    "features": [
      "컴포넌트 라이브러리",
      "반응형 디자인",
      "디자인 토큰",
      "문서화"
    ]
  },
  {
    "id": "5",
    "title": "게임 아이템 거래 플랫폼",
    "description": "게임 아이템 거래플랫폼 웹사이트 입니다.",
    "image": "/mania.jpg",
    "thumbnail": "/mania.jpg",
    "tags": ["웹사이트", "게임 아이템 거래 솔루션", "플랫폼"],
    "category": "웹 개발",
    "liveUrl": "https://www.itemmania.com/",
    "longDescription": "게임 아이템 거래플랫폼 웹사이트 입니다. 게임 아이템 거래 솔루션을 제공 하기위한 다양한 기능들이 포함되어 있습니다.",
    "technologies": ["Javascript", "jQuery", "PHP"],
    "features": [
      "게임 아이템 거래 솔루션",
      "이벤트/프로모션",
      "Canvas 기반 시세 차트 제공",
      "게임이름 검색 자동완성 모듈",
      "Carousel 모듈",
      "복권 긁기 모듈"
    ]
  },
  {
    "id": "9",
    "title": "컴퓨터 도소매업 이커머스 플랫폼",
    "description": "컴퓨터 도소매업 이커머스 플랫폼 웹사이트 입니다.",
    "longDescription": "컴퓨터 도소매업 이커머스 플랫폼 웹사이트 입니다. 컴퓨터 도소매업 이커머스 플랫폼 솔루션을 제공 하기위한 다양한 기능들이 포함되어 있습니다.",
    "image": "/jooyon.jpg",
    "thumbnail": "/jooyon.jpg",
    "tags": ["e-commerce", "쇼핑몰", "모바일 최적화", "컴퓨터"],
    "category": "웹 개발",
    "liveUrl": "https://www.jooyon.co.kr/main.php",
    "technologies": ["Javascript", "jQuery", "PHP", "CSS3"],
    "features": [
      "컴퓨터 도소매업 이커머스 플랫폼 솔루션",
      "이벤트/프로모션",
      "회사 소개",
      "공시 정보",
      "게시판",
      "인터렉션",
      "뉴스"
    ]
  }
]
